mlinsightlab/MLILClient.py
mlinsightlab/MLILException.py
mlinsightlab/ModelManager.py
mlinsightlab/__init__.py
mlinsightlab/data_mgmt.py
mlinsightlab/endpoints.py
mlinsightlab/key_mgmt.py
mlinsightlab/model_mgmt.py
mlinsightlab/platform_mgmt.py
mlinsightlab/user_mgmt.py
mlinsightlab/utils.py
mlinsightlab-0.0.36.dist-info/licenses/LICENSE
mlinsightlab-0.0.36.dist-info/METADATA
mlinsightlab-0.0.36.dist-info/WHEEL
mlinsightlab-0.0.36.dist-info/top_level.txt
mlinsightlab-0.0.36.dist-info/RECORD
