Metadata-Version: 2.4
Name: mlinsightlab
Version: 0.0.36
Summary: Your Open Source Data Science and MLOps Platform
Home-page: https://github.com/MLInsightLab/MLInsightLab-Python-SDK
Author: MLIL Team
Classifier: Programming Language :: Python :: 3
Classifier: License :: OSI Approved :: Apache Software License
Classifier: Operating System :: OS Independent
Requires-Python: >=3.6
License-File: LICENSE
Requires-Dist: sphinx-rtd-theme
Requires-Dist: myst-parser
Requires-Dist: requests
Requires-Dist: pandas
Requires-Dist: sphinx
Requires-Dist: docker
Requires-Dist: ollama
Requires-Dist: boto3
Dynamic: author
Dynamic: classifier
Dynamic: description
Dynamic: description-content-type
Dynamic: home-page
Dynamic: license-file
Dynamic: requires-dist
Dynamic: requires-python
Dynamic: summary
